{
  "products": [
    {
      "id": "1",
      "code": "code",
      "libelle": "Bordguenaaa",
      "prixUnitaire": "530",
      "categorie": "Food",
      "photo": "orange.jpg"
    },
    {
      "id": "2",
      "code": "code",
      "libelle": "L'avionde",
      "prixUnitaire": "11",
      "categorie": "Food",
      "photo": "meat.jpg"
    },
    {
      "id": "3",
      "code": "code",
      "libelle": "Jus",
      "prixUnitaire": "76",
      "categorie": "Food",
      "photo": "juice.jpg"
    },
    {
      "id": "4",
      "code": "code",
      "libelle": "Ghalla chey7a",
      "prixUnitaire": "851",
      "categorie": "Food",
      "photo": "dryfruit.jpg"
    },
    {
      "id": "5",
      "code": "code",
      "libelle": "Jus ekher",
      "prixUnitaire": 66,
      "categorie": "Food",
      "photo": "juice.jpg"
    },
    {
      "id": "6",
      "code": "code",
      "libelle": "L7am",
      "prixUnitaire": 10,
      "categorie": "Food",
      "photo": "meat.jpg"
    },
    {
      "libelle": "New Thing",
      "prixUnitaire": "888",
      "photo": "orange.jpg",
      "categorie": "food",
      "id": "uVf9Ak9"
    }
  ]
}